filetreesubs/__init__.py
filetreesubs/__main__.py
filetreesubs/subs.py
filetreesubs/utils.py
filetreesubs-1.2.0.dist-info/METADATA
filetreesubs-1.2.0.dist-info/WHEEL
filetreesubs-1.2.0.dist-info/entry_points.txt
filetreesubs-1.2.0.dist-info/licenses/LICENSES/MIT.txt
filetreesubs-1.2.0.dist-info/RECORD
