Metadata-Version: 2.1
Name: filetreesubs
Version: 1.2.0
Summary: Synchronize a file tree with text file substitutions
Project-URL: Source code, https://github.com/felixfontein/filetreesubs
Project-URL: Bug tracker, https://github.com/felixfontein/filetreesubs/issues
Author-email: Felix Fontein <felix@fontein.de>
License-Expression: MIT
License-File: LICENSES/MIT.txt
Classifier: Development Status :: 5 - Production/Stable
Classifier: Intended Audience :: Developers
Classifier: Intended Audience :: End Users/Desktop
Classifier: License :: OSI Approved :: MIT License
Classifier: Programming Language :: Python :: 3.9
Classifier: Programming Language :: Python :: 3.10
Classifier: Programming Language :: Python :: 3.11
Classifier: Topic :: Internet :: WWW/HTTP :: Site Management
Classifier: Topic :: Software Development :: Build Tools
Classifier: Topic :: Text Processing
Classifier: Topic :: Utilities
Requires-Python: >=3.9
Requires-Dist: doit>=0.36.0
Requires-Dist: pyyaml
Provides-Extra: codeqa
Requires-Dist: flake8>=6.0.0; extra == 'codeqa'
Requires-Dist: pylint>=2.17.4; extra == 'codeqa'
Requires-Dist: reuse; extra == 'codeqa'
Provides-Extra: coverage
Requires-Dist: coverage[toml]; extra == 'coverage'
Provides-Extra: dev
Requires-Dist: filetreesubs[codeqa]; extra == 'dev'
Requires-Dist: filetreesubs[formatters]; extra == 'dev'
Requires-Dist: nox; extra == 'dev'
Provides-Extra: formatters
Requires-Dist: black; extra == 'formatters'
Requires-Dist: isort; extra == 'formatters'
Provides-Extra: test
Requires-Dist: pytest; extra == 'test'
Requires-Dist: pytest-cov; extra == 'test'
Requires-Dist: pytest-error-for-skips; extra == 'test'
